Compiled from "DeptCoyPltMapController.java"
public class com.bionova.controller.DeptCoyPltMapController {
  private com.bionova.repository.DeptCoyPltMapRepository deptCoyPltMapRepository;

  private com.bionova.repository.DepartmentRepository departmentRepository;

  public com.bionova.controller.DeptCoyPltMapController();
    Code:
       0: aload_0
       1: invokespecial #1                  // Method java/lang/Object."<init>":()V
       4: return

  public java.util.List<com.bionova.entity.DeptCoyPltMap> getAllMappings();
    Code:
       0: aload_0
       1: getfield      #7                  // Field deptCoyPltMapRepository:Lcom/bionova/repository/DeptCoyPltMapRepository;
       4: invokeinterface #13,  1           // InterfaceMethod com/bionova/repository/DeptCoyPltMapRepository.findAll:()Ljava/util/List;
       9: areturn

  public org.springframework.http.ResponseEntity<com.bionova.entity.DeptCoyPltMap> createMapping(com.bionova.entity.DeptCoyPltMap);
    Code:
       0: aload_0
       1: getfield      #7                  // Field deptCoyPltMapRepository:Lcom/bionova/repository/DeptCoyPltMapRepository;
       4: aload_1
       5: invokevirtual #19                 // Method com/bionova/entity/DeptCoyPltMap.getCoyId:()Ljava/lang/Long;
       8: aload_1
       9: invokevirtual #25                 // Method com/bionova/entity/DeptCoyPltMap.getPltId:()Ljava/lang/Long;
      12: aload_1
      13: invokevirtual #28                 // Method com/bionova/entity/DeptCoyPltMap.getDeptId:()Ljava/lang/Long;
      16: invokeinterface #31,  4           // InterfaceMethod com/bionova/repository/DeptCoyPltMapRepository.findByCoyIdAndPltIdAndDeptId:(Ljava/lang/Long;Ljava/lang/Long;Ljava/lang/Long;)Ljava/util/Optional;
      21: astore_2
      22: aload_2
      23: invokevirtual #35                 // Method java/util/Optional.isPresent:()Z
      26: ifeq          70
      29: aload_2
      30: invokevirtual #41                 // Method java/util/Optional.get:()Ljava/lang/Object;
      33: checkcast     #20                 // class com/bionova/entity/DeptCoyPltMap
      36: astore_3
      37: aload_3
      38: aload_1
      39: invokevirtual #45                 // Method com/bionova/entity/DeptCoyPltMap.getSts:()Ljava/lang/Boolean;
      42: invokevirtual #49                 // Method com/bionova/entity/DeptCoyPltMap.setSts:(Ljava/lang/Boolean;)V
      45: getstatic     #53                 // Field org/springframework/http/HttpStatus.CREATED:Lorg/springframework/http/HttpStatus;
      48: invokestatic  #59                 // Method org/springframework/http/ResponseEntity.status:(Lorg/springframework/http/HttpStatusCode;)Lorg/springframework/http/ResponseEntity$BodyBuilder;
      51: aload_0
      52: getfield      #7                  // Field deptCoyPltMapRepository:Lcom/bionova/repository/DeptCoyPltMapRepository;
      55: aload_3
      56: invokeinterface #65,  2           // InterfaceMethod com/bionova/repository/DeptCoyPltMapRepository.save:(Ljava/lang/Object;)Ljava/lang/Object;
      61: checkcast     #20                 // class com/bionova/entity/DeptCoyPltMap
      64: invokeinterface #69,  2           // InterfaceMethod org/springframework/http/ResponseEntity$BodyBuilder.body:(Ljava/lang/Object;)Lorg/springframework/http/ResponseEntity;
      69: areturn
      70: getstatic     #53                 // Field org/springframework/http/HttpStatus.CREATED:Lorg/springframework/http/HttpStatus;
      73: invokestatic  #59                 // Method org/springframework/http/ResponseEntity.status:(Lorg/springframework/http/HttpStatusCode;)Lorg/springframework/http/ResponseEntity$BodyBuilder;
      76: aload_0
      77: getfield      #7                  // Field deptCoyPltMapRepository:Lcom/bionova/repository/DeptCoyPltMapRepository;
      80: aload_1
      81: invokeinterface #65,  2           // InterfaceMethod com/bionova/repository/DeptCoyPltMapRepository.save:(Ljava/lang/Object;)Ljava/lang/Object;
      86: checkcast     #20                 // class com/bionova/entity/DeptCoyPltMap
      89: invokeinterface #69,  2           // InterfaceMethod org/springframework/http/ResponseEntity$BodyBuilder.body:(Ljava/lang/Object;)Lorg/springframework/http/ResponseEntity;
      94: areturn

  public org.springframework.http.ResponseEntity<com.bionova.entity.DeptCoyPltMap> updateMapping(java.lang.Long, com.bionova.entity.DeptCoyPltMap);
    Code:
       0: aload_0
       1: getfield      #7                  // Field deptCoyPltMapRepository:Lcom/bionova/repository/DeptCoyPltMapRepository;
       4: aload_1
       5: invokeinterface #75,  2           // InterfaceMethod com/bionova/repository/DeptCoyPltMapRepository.findById:(Ljava/lang/Object;)Ljava/util/Optional;
      10: aload_1
      11: invokedynamic #79,  0             // InvokeDynamic #0:get:(Ljava/lang/Long;)Ljava/util/function/Supplier;
      16: invokevirtual #82                 // Method java/util/Optional.orElseThrow:(Ljava/util/function/Supplier;)Ljava/lang/Object;
      19: checkcast     #20                 // class com/bionova/entity/DeptCoyPltMap
      22: astore_3
      23: aload_3
      24: aload_2
      25: invokevirtual #19                 // Method com/bionova/entity/DeptCoyPltMap.getCoyId:()Ljava/lang/Long;
      28: invokevirtual #86                 // Method com/bionova/entity/DeptCoyPltMap.setCoyId:(Ljava/lang/Long;)V
      31: aload_3
      32: aload_2
      33: invokevirtual #25                 // Method com/bionova/entity/DeptCoyPltMap.getPltId:()Ljava/lang/Long;
      36: invokevirtual #90                 // Method com/bionova/entity/DeptCoyPltMap.setPltId:(Ljava/lang/Long;)V
      39: aload_3
      40: aload_2
      41: invokevirtual #28                 // Method com/bionova/entity/DeptCoyPltMap.getDeptId:()Ljava/lang/Long;
      44: invokevirtual #93                 // Method com/bionova/entity/DeptCoyPltMap.setDeptId:(Ljava/lang/Long;)V
      47: aload_3
      48: aload_2
      49: invokevirtual #45                 // Method com/bionova/entity/DeptCoyPltMap.getSts:()Ljava/lang/Boolean;
      52: invokevirtual #49                 // Method com/bionova/entity/DeptCoyPltMap.setSts:(Ljava/lang/Boolean;)V
      55: aload_0
      56: getfield      #7                  // Field deptCoyPltMapRepository:Lcom/bionova/repository/DeptCoyPltMapRepository;
      59: aload_3
      60: invokeinterface #65,  2           // InterfaceMethod com/bionova/repository/DeptCoyPltMapRepository.save:(Ljava/lang/Object;)Ljava/lang/Object;
      65: checkcast     #20                 // class com/bionova/entity/DeptCoyPltMap
      68: invokestatic  #96                 // Method org/springframework/http/ResponseEntity.ok:(Ljava/lang/Object;)Lorg/springframework/http/ResponseEntity;
      71: areturn

  public org.springframework.http.ResponseEntity<?> deleteMapping(java.lang.Long);
    Code:
       0: aload_0
       1: getfield      #7                  // Field deptCoyPltMapRepository:Lcom/bionova/repository/DeptCoyPltMapRepository;
       4: aload_1
       5: invokeinterface #99,  2           // InterfaceMethod com/bionova/repository/DeptCoyPltMapRepository.deleteById:(Ljava/lang/Object;)V
      10: invokestatic  #103                // Method org/springframework/http/ResponseEntity.ok:()Lorg/springframework/http/ResponseEntity$BodyBuilder;
      13: invokeinterface #106,  1          // InterfaceMethod org/springframework/http/ResponseEntity$BodyBuilder.build:()Lorg/springframework/http/ResponseEntity;
      18: areturn

  public java.util.List<com.bionova.entity.DepartmentMaster> getDepartmentsByCompany(java.lang.Long);
    Code:
       0: aload_0
       1: getfield      #7                  // Field deptCoyPltMapRepository:Lcom/bionova/repository/DeptCoyPltMapRepository;
       4: aload_1
       5: invokeinterface #110,  2          // InterfaceMethod com/bionova/repository/DeptCoyPltMapRepository.findByCoyId:(Ljava/lang/Long;)Ljava/util/List;
      10: astore_2
      11: aload_2
      12: invokeinterface #114,  1          // InterfaceMethod java/util/List.stream:()Ljava/util/stream/Stream;
      17: invokedynamic #120,  0            // InvokeDynamic #1:test:()Ljava/util/function/Predicate;
      22: invokeinterface #124,  2          // InterfaceMethod java/util/stream/Stream.filter:(Ljava/util/function/Predicate;)Ljava/util/stream/Stream;
      27: invokedynamic #130,  0            // InvokeDynamic #2:apply:()Ljava/util/function/Function;
      32: invokeinterface #134,  2          // InterfaceMethod java/util/stream/Stream.map:(Ljava/util/function/Function;)Ljava/util/stream/Stream;
      37: invokeinterface #138,  1          // InterfaceMethod java/util/stream/Stream.toList:()Ljava/util/List;
      42: astore_3
      43: aload_0
      44: getfield      #141                // Field departmentRepository:Lcom/bionova/repository/DepartmentRepository;
      47: aload_3
      48: invokeinterface #145,  2          // InterfaceMethod com/bionova/repository/DepartmentRepository.findAllById:(Ljava/lang/Iterable;)Ljava/util/List;
      53: areturn

  public java.util.List<com.bionova.entity.DepartmentMaster> getDepartmentsByCompanyAndPlant(java.lang.Long, java.lang.Long);
    Code:
       0: aload_0
       1: getfield      #7                  // Field deptCoyPltMapRepository:Lcom/bionova/repository/DeptCoyPltMapRepository;
       4: aload_1
       5: aload_2
       6: invokeinterface #151,  3          // InterfaceMethod com/bionova/repository/DeptCoyPltMapRepository.findByCoyIdAndPltId:(Ljava/lang/Long;Ljava/lang/Long;)Ljava/util/List;
      11: astore_3
      12: aload_3
      13: invokeinterface #114,  1          // InterfaceMethod java/util/List.stream:()Ljava/util/stream/Stream;
      18: invokedynamic #120,  0            // InvokeDynamic #1:test:()Ljava/util/function/Predicate;
      23: invokeinterface #124,  2          // InterfaceMethod java/util/stream/Stream.filter:(Ljava/util/function/Predicate;)Ljava/util/stream/Stream;
      28: invokedynamic #130,  0            // InvokeDynamic #2:apply:()Ljava/util/function/Function;
      33: invokeinterface #134,  2          // InterfaceMethod java/util/stream/Stream.map:(Ljava/util/function/Function;)Ljava/util/stream/Stream;
      38: invokeinterface #138,  1          // InterfaceMethod java/util/stream/Stream.toList:()Ljava/util/List;
      43: astore        4
      45: aload_0
      46: getfield      #141                // Field departmentRepository:Lcom/bionova/repository/DepartmentRepository;
      49: aload         4
      51: invokeinterface #145,  2          // InterfaceMethod com/bionova/repository/DepartmentRepository.findAllById:(Ljava/lang/Iterable;)Ljava/util/List;
      56: areturn

  private static java.lang.RuntimeException lambda$updateMapping$0(java.lang.Long);
    Code:
       0: new           #155                // class java/lang/RuntimeException
       3: dup
       4: aload_0
       5: invokedynamic #157,  0            // InvokeDynamic #3:makeConcatWithConstants:(Ljava/lang/Long;)Ljava/lang/String;
      10: invokespecial #161                // Method java/lang/RuntimeException."<init>":(Ljava/lang/String;)V
      13: areturn
}
